wshubsapi/__init__.py
wshubsapi/client_in_hub.py
wshubsapi/comm_environment.py
wshubsapi/connected_client.py
wshubsapi/connected_clients_group.py
wshubsapi/connected_clients_holder.py
wshubsapi/function_message.py
wshubsapi/hub.py
wshubsapi/hubs_inspector.py
wshubsapi/message_separator.py
wshubsapi/serializer.py
wshubsapi/utils.py
wshubsapi/utils_api_hub.py
wshubsapi/validate_strings.py
wshubsapi/client_file_generator/__init__.py
wshubsapi/client_file_generator/client_file_generator.py
wshubsapi/client_file_generator/cpp_file_generator.py
wshubsapi/client_file_generator/dart_file_generator.py
wshubsapi/client_file_generator/java_file_generator.py
wshubsapi/client_file_generator/js_file_generator.py
wshubsapi/client_file_generator/python_file_generator.py
wshubsapi/client_file_generator/JavaExtraFiles/Base64.java
wshubsapi/client_file_generator/JavaExtraFiles/ClientBase.java
wshubsapi/client_file_generator/JavaExtraFiles/FunctionResult.java
wshubsapi/client_file_generator/JavaExtraFiles/WSHubsAPIClient.java
wshubsapi/client_file_generator/JavaExtraFiles/WSHubsEventHandler.java
wshubsapi/client_file_generator/JavaExtraFiles/WebSocket.java
wshubsapi/client_file_generator/JavaExtraFiles/WebSocketEventHandler.java
wshubsapi/client_file_generator/JavaExtraFiles/WebSocketException.java
wshubsapi/client_file_generator/JavaExtraFiles/WebSocketHandshake.java
wshubsapi/client_file_generator/JavaExtraFiles/WebSocketMessage.java
wshubsapi/client_file_generator/JavaExtraFiles/WebSocketReceiver.java
wshubsapi/client_file_generator/JavaExtraFiles/__init__.py
wshubsapi/connection_handlers/__init__.py
wshubsapi/connection_handlers/request_handler.py
wshubsapi/connection_handlers/socket_handler.py
wshubsapi/connection_handlers/tornado_handler.py
wshubsapi/connection_handlers/ws4py_handler.py
wshubsapi/examples/LoggingHandlers.py
wshubsapi/examples/__init__.py
wshubsapi/examples/Clients/__init__.py
wshubsapi/examples/Clients/jsClient.html
wshubsapi-0.9.5.dist-info/DESCRIPTION.rst
wshubsapi-0.9.5.dist-info/METADATA
wshubsapi-0.9.5.dist-info/RECORD
wshubsapi-0.9.5.dist-info/WHEEL
wshubsapi-0.9.5.dist-info/metadata.json
wshubsapi-0.9.5.dist-info/top_level.txt
