Metadata-Version: 2.0
Name: wshubsapi
Version: 0.9.5
Summary: make complex web-socket communication in a simple way
Home-page: https://github.com/JorgeGarciaIrazabal/WSHubsAPI.git
Author: Jorge Garcia Irazabal
Author-email: jorge.girazabal@gmail.com
License: MIT
Keywords: communication protocol tornado django sockets signalR websockets Android Java javascript API
Platform: UNKNOWN
Classifier: Development Status :: 4 - Beta
Classifier: Intended Audience :: Developers
Classifier: Topic :: Software Development :: Build Tools
Classifier: License :: OSI Approved :: MIT License
Classifier: Programming Language :: Python :: 3.4
Classifier: Programming Language :: Python :: 3.5
Requires-Dist: futures
Requires-Dist: inflection (==0.3.1)
Requires-Dist: ws4py
